jupyter_idle/__init__.py
jupyter_idle/handler.py
jupyter_idle/tests/__init__.py
jupyter_idle/tests/test_handlers.py
jupyter_idle-0.1.1.data/data/etc/jupyter/jupyter_server_config.d/jupyter_idle.json
jupyter_idle-0.1.1.dist-info/LICENSE
jupyter_idle-0.1.1.dist-info/METADATA
jupyter_idle-0.1.1.dist-info/WHEEL
jupyter_idle-0.1.1.dist-info/top_level.txt
jupyter_idle-0.1.1.dist-info/RECORD
