Metadata-Version: 2.1
Name: jupyter-idle
Version: 0.1.1
Summary: Jupyter Server Extension for checking last activity time
Home-page: https://aws.amazon.com/sagemaker/
Author: Amazon
License: Amazon Software License
Keywords: Jupyter,JupyterLab
Platform: Linux
Platform: Mac OS X
Platform: Windows
Classifier: Programming Language :: Python
Classifier: Programming Language :: Python :: 3
Classifier: Programming Language :: Python :: 3.9
Classifier: Framework :: Jupyter
Requires-Python: >=3.9
License-File: LICENSE
Requires-Dist: jupyter-server >=2.0.0
Requires-Dist: tornado
Provides-Extra: dev
Requires-Dist: pytest >=6 ; extra == 'dev'
Requires-Dist: pytest-cov ; extra == 'dev'
Requires-Dist: black ; extra == 'dev'
Requires-Dist: pytest-jupyter ; extra == 'dev'
